ruamel.std.zipfile-0.1.0-py2.7-nspkg.pth
ruamel/std/zipfile/__init__.py
ruamel.std.zipfile-0.1.0.dist-info/DESCRIPTION.rst
ruamel.std.zipfile-0.1.0.dist-info/METADATA
ruamel.std.zipfile-0.1.0.dist-info/RECORD
ruamel.std.zipfile-0.1.0.dist-info/WHEEL
ruamel.std.zipfile-0.1.0.dist-info/metadata.json
ruamel.std.zipfile-0.1.0.dist-info/namespace_packages.txt
ruamel.std.zipfile-0.1.0.dist-info/top_level.txt
