Metadata-Version: 2.0
Name: ruamel.std.zipfile
Version: 0.1.0
Summary: improvements over the standard zipfile package
Home-page: https://bitbucket.org/ruamel/std.zipfile
Author: Anthon van der Neut
Author-email: a.van.der.neut@ruamel.eu
License: MIT License
Platform: UNKNOWN
Classifier: Development Status :: 4 - Beta
Classifier: Intended Audience :: Developers
Classifier: License :: OSI Approved :: MIT License
Classifier: Operating System :: OS Independent
Classifier: Programming Language :: Python
